aily/__init__.py
aily/__version__.py
aily/main.py
aily/models.py
aily/db/__init__.py
aily/db/crud.py
aily/db/main.py
aily/hardwares/__init__.py
aily/hardwares/audio.py
aily/hardwares/tts.py
aily/llm/__init__.py
aily/llm/llm.py
aily/llm/text_generation.py
aily/llm/vision.py
aily/tools/__init__.py
aily/tools/speech_to_text.py
aily/tools/speex_decoder.py
aily/tools/text_to_speech.py
aily/tools/tools.py
examples/__init__.py
examples/aily_tts.py
examples/conversation_records.py
examples/custom_invoke.py
examples/custom_invoke_vision.py
examples/example.py
examples/function_calls.py
examples/wait_words.py
aily_py-2.0.1.dist-info/LICENSE
aily_py-2.0.1.dist-info/METADATA
aily_py-2.0.1.dist-info/WHEEL
aily_py-2.0.1.dist-info/top_level.txt
aily_py-2.0.1.dist-info/RECORD
