Metadata-Version: 2.1
Name: aily-py
Version: 2.0.1
Summary: Aily CLI
Home-page: https://aily.pro
Author: stao
Author-email: werewolf_st@hotmail.com
Classifier: Programming Language :: Python :: 3
License-File: LICENSE
Requires-Dist: python-dotenv ==1.0.1
Requires-Dist: aiohttp ==3.9.3
Requires-Dist: reactivex ==4.0.4
Requires-Dist: tiktoken ==0.6.0
Requires-Dist: tenacity ==8.2.3
Requires-Dist: SpeechRecognition
Requires-Dist: loguru
Requires-Dist: requests
Requires-Dist: pyserial
Requires-Dist: openai
Requires-Dist: baidu-aip
Requires-Dist: chardet
Requires-Dist: edge-tts ==6.1.10
